requests_staticmock/__init__.py
requests_staticmock/abstractions.py
requests_staticmock/adapter.py
requests_staticmock/context.py
requests_staticmock/responses.py
requests_staticmock-1.4.0.dist-info/DESCRIPTION.rst
requests_staticmock-1.4.0.dist-info/METADATA
requests_staticmock-1.4.0.dist-info/RECORD
requests_staticmock-1.4.0.dist-info/WHEEL
requests_staticmock-1.4.0.dist-info/metadata.json
requests_staticmock-1.4.0.dist-info/top_level.txt
